typeddfs/__init__.py
typeddfs/_core_dfs.py
typeddfs/_entries.py
typeddfs/_mixins/__init__.py
typeddfs/_mixins/_csv_like_mixin.py
typeddfs/_mixins/_dataclass_mixin.py
typeddfs/_mixins/_excel_mixins.py
typeddfs/_mixins/_feather_parquet_hdf_mixin.py
typeddfs/_mixins/_flexwf_mixin.py
typeddfs/_mixins/_formatted_mixin.py
typeddfs/_mixins/_full_io_mixin.py
typeddfs/_mixins/_fwf_mixin.py
typeddfs/_mixins/_ini_like_mixin.py
typeddfs/_mixins/_json_xml_mixin.py
typeddfs/_mixins/_lines_mixin.py
typeddfs/_mixins/_new_methods_mixin.py
typeddfs/_mixins/_pickle_mixin.py
typeddfs/_mixins/_pretty_print_mixin.py
typeddfs/_mixins/_retype_mixin.py
typeddfs/_pretty_dfs.py
typeddfs/abs_dfs.py
typeddfs/base_dfs.py
typeddfs/builders.py
typeddfs/datasets.py
typeddfs/df_errors.py
typeddfs/df_typing.py
typeddfs/example.py
typeddfs/file_formats.py
typeddfs/frozen_types.py
typeddfs/matrix_dfs.py
typeddfs/typed_dfs.py
typeddfs/untyped_dfs.py
typeddfs/utils/__init__.py
typeddfs/utils/_format_support.py
typeddfs/utils/_utils.py
typeddfs/utils/checksum_models.py
typeddfs/utils/checksums.py
typeddfs/utils/cli_help.py
typeddfs/utils/dtype_utils.py
typeddfs/utils/io_utils.py
typeddfs/utils/json_utils.py
typeddfs/utils/misc_utils.py
typeddfs/utils/parse_utils.py
typeddfs/utils/sort_utils.py
typeddfs-0.16.5.dist-info/LICENSE.txt
typeddfs-0.16.5.dist-info/WHEEL
typeddfs-0.16.5.dist-info/METADATA
typeddfs-0.16.5.dist-info/RECORD
