Metadata-Version: 2.1
Name: typeddfs
Version: 0.16.5
Summary: Pandas DataFrame subclasses that enforce structure and can self-organize.
Home-page: https://github.com/dmyersturnbull/typed-dfs
License: Apache-2.0
Keywords: pandas,typing,columns,structured
Author: Douglas Myers-Turnbull
Maintainer: dmyersturnbull
Requires-Python: >=3.8,<4.0
Classifier: Development Status :: 4 - Beta
Classifier: Environment :: Console
Classifier: Intended Audience :: Developers
Classifier: License :: OSI Approved :: Apache Software License
Classifier: Natural Language :: English
Classifier: Operating System :: OS Independent
Classifier: Programming Language :: Python :: 3
Classifier: Programming Language :: Python :: 3 :: Only
Classifier: Programming Language :: Python :: 3.10
Classifier: Programming Language :: Python :: 3.8
Classifier: Programming Language :: Python :: 3.9
Classifier: Topic :: Software Development :: Libraries :: Python Modules
Provides-Extra: all
Provides-Extra: excel
Provides-Extra: feather
Provides-Extra: html
Provides-Extra: main
Provides-Extra: parquet
Provides-Extra: toml
Provides-Extra: xlsb
Provides-Extra: xml
Requires-Dist: beautifulsoup4 (>=4); extra == "html" or extra == "all"
Requires-Dist: html5lib (>=1); extra == "html" or extra == "all"
Requires-Dist: lxml (>=4); extra == "xml" or extra == "main" or extra == "all"
Requires-Dist: natsort (>=8)
Requires-Dist: openpyxl (>=3); extra == "excel" or extra == "main" or extra == "all"
Requires-Dist: orjson (>=3.6,<4.0)
Requires-Dist: pandas (>=1.3,<2.0)
Requires-Dist: pyarrow (>=5); extra == "feather" or extra == "parquet" or extra == "main" or extra == "all"
Requires-Dist: pyxlsb (>=1); extra == "xlsb" or extra == "all"
Requires-Dist: regex (>=2022)
Requires-Dist: tabulate (>=0.8,<0.9)
Requires-Dist: tomlkit (>=0.7); extra == "toml" or extra == "main" or extra == "all"
Requires-Dist: wcwidth (>=0.2)
Project-URL: CI, https://github.com/dmyersturnbull/typed-dfs/actions
Project-URL: Documentation, https://typed-dfs.readthedocs.io
Project-URL: Download, https://pypi.org/project/typeddfs/
Project-URL: Issues, https://github.com/dmyersturnbull/typed-dfs/issues
Project-URL: Repository, https://github.com/dmyersturnbull/typed-dfs
